setup.py
distributions_bk/Binomialdistribution.py
distributions_bk/Gaussiandistribution.py
distributions_bk/Generaldistribution.py
distributions_bk/__init__.py
distributions_bk.egg-info/PKG-INFO
distributions_bk.egg-info/SOURCES.txt
distributions_bk.egg-info/dependency_links.txt
distributions_bk.egg-info/not-zip-safe
distributions_bk.egg-info/top_level.txt